README.md
setup.py
alphav/__init__.py
alphav/data.py
alphav/symbol.py
alphav.egg-info/PKG-INFO
alphav.egg-info/SOURCES.txt
alphav.egg-info/dependency_links.txt
alphav.egg-info/requires.txt
alphav.egg-info/top_level.txt