Metadata-Version: 2.1
Name: alphav
Version: 1.0.4
Summary: alpha vantage api wrapper
Home-page: https://github.com/dt-ss/alphav
Author: daniel tal
Author-email: daniel@dtsoft.co.il
License: UNKNOWN
Platform: UNKNOWN
Classifier: Programming Language :: Python :: 3
Classifier: License :: OSI Approved :: MIT License
Classifier: Operating System :: OS Independent
Requires: setuptools
Requires-Python: >=3.7
